README.md
setup.py
minorimpact/__init__.py
minorimpact/config.py
minorimpact/curses.py
minorimpact.egg-info/PKG-INFO
minorimpact.egg-info/SOURCES.txt
minorimpact.egg-info/dependency_links.txt
minorimpact.egg-info/requires.txt
minorimpact.egg-info/top_level.txt